pyprotista/__init__.py
pyprotista/unify.py
pyprotista/utils.py
pyprotista/version.txt
pyprotista/parsers/__init__.py
pyprotista/parsers/base_parser.py
pyprotista/parsers/ident_base_parser.py
pyprotista/parsers/misc.py
pyprotista/parsers/quant_base_parser.py
pyprotista/parsers/ident/__init__.py
pyprotista/parsers/ident/comet_2020_01_4_parser.py
pyprotista/parsers/ident/dummy_parser.py
pyprotista/parsers/ident/mascot_2_6_2_parser.py
pyprotista/parsers/ident/msamanda_2_parser.py
pyprotista/parsers/ident/msfragger_3_parser.py
pyprotista/parsers/ident/msgfplus_2021_03_22_parser.py
pyprotista/parsers/ident/omssa_2_1_9_parser.py
pyprotista/parsers/ident/xtandem_alanine.py
pyprotista/parsers/models/base_parser_model.json
pyprotista/parsers/models/ident_parser_model.json
pyprotista/parsers/models/quant_parser_model.json
pyprotista/parsers/quant/__init__.py
pyprotista/parsers/quant/flash_lfq_1_2_0_parser.py
pyProtista-1.8.3.dist-info/AUTHORS.TXT
pyProtista-1.8.3.dist-info/LICENSE
pyProtista-1.8.3.dist-info/METADATA
pyProtista-1.8.3.dist-info/WHEEL
pyProtista-1.8.3.dist-info/top_level.txt
pyProtista-1.8.3.dist-info/RECORD
